[
  {
    "line": 2,
    "elements": [
      {
        "line": 4,
        "name": "",
        "description": "",
        "type": "background",
        "keyword": "Background",
        "steps": [
          {
            "result": {
              "duration": 2083034262,
              "status": "passed"
            },
            "line": 5,
            "name": "User is on Retail website",
            "match": {
              "location": "LoginTestStepDefinition.user_is_on_Retail_website()"
            },
            "keyword": "Given "
          },
          {
            "result": {
              "duration": 667300833,
              "status": "passed"
            },
            "line": 6,
            "name": "User click on the desktop",
            "match": {
              "location": "Capstone1StDef.user_click_on_the_desktop()"
            },
            "keyword": "When "
          },
          {
            "result": {
              "duration": 1139536891,
              "status": "passed"
            },
            "line": 7,
            "name": "User click on all desktop",
            "match": {
              "location": "Capstone1StDef.user_click_on_all_desktop()"
            },
            "keyword": "And "
          }
        ]
      },
      {
        "before": [
          {
            "result": {
              "duration": 2813655992,
              "status": "passed"
            },
            "match": {
              "location": "Initializer.beforeHooks(Scenario)"
            }
          }
        ],
        "line": 10,
        "name": "Retail page Items verifing",
        "description": "",
        "id": "items-on-the-retail-page-test;retail-page-items-verifing",
        "after": [
          {
            "result": {
              "duration": 229619621,
              "status": "passed"
            },
            "match": {
              "location": "Initializer.afterHooks(Scenario)"
            }
          }
        ],
        "type": "scenario",
        "keyword": "Scenario",
        "steps": [
          {
            "result": {
              "duration": 517764590,
              "status": "passed"
            },
            "line": 11,
            "name": "User should all items are present in Desktop page",
            "match": {
              "location": "Capstone1StDef.user_should_all_items_are_present_in_Desktop_page()"
            },
            "keyword": "Then "
          }
        ],
        "tags": [
          {
            "line": 9,
            "name": "@Test44"
          }
        ]
      }
    ],
    "name": "Items on the retail page test",
    "description": "",
    "id": "items-on-the-retail-page-test",
    "keyword": "Feature",
    "uri": "Features/Capstone1.feature",
    "tags": [
      {
        "line": 1,
        "name": "@CapStoneTest"
      }
    ]
  }
]